{
  "kind": "collectionType",
  "collectionName": "api_keys",
  "info": {
    "singularName": "api-key",
    "pluralName": "api-keys",
    "displayName": "API Keys",
    "description": ""
  },
  "options": {
    "draftAndPublish": true
  },
  "pluginOptions": {},
  "attributes": {
    "Nickname": {
      "type": "string",
      "required": true,
      "unique": true
    },
    "Role": {
      "type": "enumeration",
      "enum": [
        "developer",
        "deployment"
      ],
      "required": true
    },
    "ApiKey": {
      "type": "string",
      "default": "placeholder"
    }
  }
}
